frozenclasses/__init__.py
frozenclasses/tests/__init__.py
frozenclasses/tests/test_1984.py
frozenclasses-0.1.1.dist-info/LICENSE.txt
frozenclasses-0.1.1.dist-info/METADATA
frozenclasses-0.1.1.dist-info/WHEEL
frozenclasses-0.1.1.dist-info/top_level.txt
frozenclasses-0.1.1.dist-info/RECORD
