Metadata-Version: 2.1
Name: frozenclasses
Version: 0.1.1
Summary: frozenclasses
Author-email: Johannes <johannes-programming@mailfence.com>, Johannes <johannes-programming@posteo.org>
License: The MIT License (MIT)
Project-URL: Documentation, https://pypi.org/project/frozenclasses
Project-URL: Download, https://pypi.org/project/frozenclasses/#files
Project-URL: Source, https://github.com/johannes-programming/frozenclasses
Classifier: Development Status :: 3 - Alpha
Classifier: License :: OSI Approved :: MIT License
Classifier: Programming Language :: Python
Classifier: Programming Language :: Python :: 3
Classifier: Programming Language :: Python :: 3 :: Only
Requires-Python: >=3.11
License-File: LICENSE.txt
